bunda/__init__.py
bunda/main_module.py
bunda/p6.py
bunda/p7.py
bunda-0.5.dist-info/METADATA
bunda-0.5.dist-info/WHEEL
bunda-0.5.dist-info/top_level.txt
bunda-0.5.dist-info/RECORD
