Metadata-Version: 2.1
Name: bunda
Version: 0.5
Summary: bunda
Home-page: https://github.com/bunda/bunda
Author: bunda
Author-email: bunda@bunda.com
Classifier: Programming Language :: Python :: 3
Classifier: License :: OSI Approved :: MIT License
Classifier: Operating System :: OS Independent
